description_generator.py
description_generator-0.1.3.dist-info/LICENSE.md
description_generator-0.1.3.dist-info/METADATA
description_generator-0.1.3.dist-info/WHEEL
description_generator-0.1.3.dist-info/entry_points.txt
description_generator-0.1.3.dist-info/top_level.txt
description_generator-0.1.3.dist-info/RECORD
